perfectcrop/.DS_Store
perfectcrop/__init__.py
perfectcrop/cli.py
perfectcrop/grid.py
perfectcrop/perfect_crop.py
perfectcrop/shots.py
perfectcrop/video_standardize.py
perfectcrop-1.1.1.dist-info/LICENSE
perfectcrop-1.1.1.dist-info/METADATA
perfectcrop-1.1.1.dist-info/WHEEL
perfectcrop-1.1.1.dist-info/entry_points.txt
perfectcrop-1.1.1.dist-info/RECORD
