Metadata-Version: 2.1
Name: perfectcrop
Version: 1.1.1
Summary: A video cropping tool for artists that detects an object, finds the average center pixel of the bounding box, and crops out from center without a decrease in video quality.
Keywords: object detection,video
Author: Rebecca Picanso
Author-email: rebeccapicansot@gmail.com
Requires-Python: >=3.8,<4.0
Classifier: Programming Language :: Python :: 3
Classifier: Programming Language :: Python :: 3.8
Classifier: Programming Language :: Python :: 3.9
Classifier: Programming Language :: Python :: 3.10
Classifier: Programming Language :: Python :: 3.11
Classifier: Programming Language :: Python :: 3.12
Classifier: Topic :: Multimedia :: Video
Classifier: Topic :: Utilities
Requires-Dist: argparse (>=1.4.0,<2.0.0)
Requires-Dist: ffmpeg (>=1.4,<2.0)
Requires-Dist: moviepy (>=1.0.3,<2.0.0)
Requires-Dist: opencv-python (>=4.8.1.78,<5.0.0.0)
Requires-Dist: scenedetect (>=0.6.2,<0.7.0)
Requires-Dist: transformers (>=4.35.2,<5.0.0)
